DStore_MySQL-0.1.0a2.dist-info/DESCRIPTION.rst
DStore_MySQL-0.1.0a2.dist-info/METADATA
DStore_MySQL-0.1.0a2.dist-info/RECORD
DStore_MySQL-0.1.0a2.dist-info/WHEEL
DStore_MySQL-0.1.0a2.dist-info/metadata.json
DStore_MySQL-0.1.0a2.dist-info/top_level.txt
dstore_mysql/MySQL2.py
dstore_mysql/MySQL3.py
dstore_mysql/MySQLStore.py
dstore_mysql/SQL.py
dstore_mysql/__init__.py
