Metadata-Version: 2.0
Name: DStore-MySQL
Version: 0.1.0a2
Summary: MySQL Storage layer for DStore
Home-page: https://github.com/MarkLark/dstore-mysql
Author: Mark Pittaway
Author-email: mark.pittaway@mlit.net.au
License: MIT
Platform: any
Classifier: Development Status :: 3 - Alpha
Classifier: Intended Audience :: Developers
Classifier: License :: OSI Approved :: MIT License
Classifier: Operating System :: OS Independent
Classifier: Programming Language :: Python
Classifier: Programming Language :: Python :: 2.7
Classifier: Programming Language :: Python :: 3.3
Classifier: Programming Language :: Python :: 3.4
Classifier: Programming Language :: Python :: 3.5
Classifier: Programming Language :: Python :: 3.6
Classifier: Topic :: Database :: Front-Ends
Requires-Dist: dstore
